adafruit_circuitpython_rsa-1.2.28.dist-info/licenses/LICENSE
adafruit_rsa/__init__.py
adafruit_rsa/_compat.py
adafruit_rsa/asn1.py
adafruit_rsa/common.py
adafruit_rsa/core.py
adafruit_rsa/key.py
adafruit_rsa/machine_size.py
adafruit_rsa/pem.py
adafruit_rsa/pkcs1.py
adafruit_rsa/prime.py
adafruit_rsa/randnum.py
adafruit_rsa/transform.py
adafruit_circuitpython_rsa-1.2.28.dist-info/METADATA
adafruit_circuitpython_rsa-1.2.28.dist-info/WHEEL
adafruit_circuitpython_rsa-1.2.28.dist-info/top_level.txt
adafruit_circuitpython_rsa-1.2.28.dist-info/RECORD
