Metadata-Version: 2.4
Name: adafruit-circuitpython-rsa
Version: 1.2.28
Summary: RSA implementation based on python-rsa
Author-email: Adafruit Industries <circuitpython@adafruit.com>
License: MIT
Project-URL: Homepage, https://github.com/adafruit/Adafruit_CircuitPython_RSA
Keywords: adafruit,blinka,circuitpython,micropython,rsa,rsa,,encryption,,cryptography
Classifier: Intended Audience :: Developers
Classifier: Topic :: Software Development :: Libraries
Classifier: Topic :: Software Development :: Embedded Systems
Classifier: Topic :: System :: Hardware
Classifier: License :: OSI Approved :: MIT License
Classifier: Programming Language :: Python :: 3
License-File: LICENSE
Requires-Dist: Adafruit-Blinka>=7.0.0
Requires-Dist: pyasn1
Requires-Dist: adafruit-circuitpython-logging>=4.0.0
Requires-Dist: adafruit-circuitpython-hashlib
Provides-Extra: optional
Dynamic: license-file
